computerender/__init__.py
computerender/__main__.py
computerender/client.py
computerender/py.typed
computerender-0.1.4.dist-info/entry_points.txt
computerender-0.1.4.dist-info/METADATA
computerender-0.1.4.dist-info/LICENSE
computerender-0.1.4.dist-info/WHEEL
computerender-0.1.4.dist-info/RECORD
