Metadata-Version: 2.1
Name: computerender
Version: 0.1.4
Summary: Computerender
Home-page: https://github.com/computerender/computerender-python
License: MIT
Author: computerender
Author-email: peter@computerender.com
Requires-Python: >=3.7,<4.0
Classifier: Development Status :: 4 - Beta
Classifier: License :: OSI Approved :: MIT License
Classifier: Programming Language :: Python :: 3
Classifier: Programming Language :: Python :: 3.7
Classifier: Programming Language :: Python :: 3.8
Classifier: Programming Language :: Python :: 3.9
Classifier: Programming Language :: Python :: 3.10
Classifier: Programming Language :: Python :: 3.11
Requires-Dist: aiohttp (>=3.8.3,<4.0.0)
Requires-Dist: click (>=8.0.1)
Project-URL: Changelog, https://github.com/computerender/computerender-python/releases
Project-URL: Documentation, https://computerender.readthedocs.io
Project-URL: Repository, https://github.com/computerender/computerender-python
